{"cameraMode":{"drawMode":0,"name":"Shaded","section":"Shading Mode"},"sceneLighting":false,"audioPlay":false,"sceneViewState":{"m_AlwaysRefresh":false,"showFog":true,"showSkybox":false,"showFlares":true,"showImageEffects":true,"showParticleSystems":true,"showVisualEffectGraphs":true,"m_FxEnabled":true},"in2DMode":false,"pivot":{"x":0.5374765396118164,"y":0.5460250377655029,"z":-0.318439781665802},"rotation":{"x":-0.16301777958869935,"y":0.7179556488990784,"z":-0.17935891449451447,"w":-0.6525346636772156},"size":0.3073950409889221,"orthographic":false}